pyweb2md/__init__.py
pyweb2md/config/__init__.py
pyweb2md/config/defaults.py
pyweb2md/core/__init__.py
pyweb2md/core/batch_scraper.py
pyweb2md/core/converter.py
pyweb2md/core/extractor.py
pyweb2md/core/navigator.py
pyweb2md/core/web2md.py
pyweb2md/utils/__init__.py
pyweb2md/utils/driver_manager.py
pyweb2md/utils/logger.py
pyweb2md/utils/text_cleaner.py
pyweb2md/utils/url_processor.py
pyweb2md-0.1.0.dist-info/licenses/LICENSE
pyweb2md-0.1.0.dist-info/METADATA
pyweb2md-0.1.0.dist-info/WHEEL
pyweb2md-0.1.0.dist-info/top_level.txt
pyweb2md-0.1.0.dist-info/RECORD
