Metadata-Version: 2.4
Name: pyweb2md
Version: 0.1.0
Summary: 专为LLM应用优化的网页内容提取和Markdown转换工具
Author-email: kian_liu <kian_liu@foxmail.com>
License: MIT License
Project-URL: Homepage, https://github.com/PyWeb2MD/pyweb2md
Project-URL: Repository, https://github.com/PyWeb2MD/pyweb2md
Project-URL: Documentation, https://github.com/PyWeb2MD/pyweb2md#readme
Project-URL: Bug Tracker, https://github.com/PyWeb2MD/pyweb2md/issues
Project-URL: Changelog, https://github.com/PyWeb2MD/pyweb2md/blob/main/CHANGELOG.md
Keywords: web scraping,markdown,llm,ai,content extraction,html to markdown,token optimization
Classifier: Development Status :: 3 - Alpha
Classifier: Intended Audience :: Developers
Classifier: Topic :: Software Development :: Libraries :: Python Modules
Classifier: Topic :: Internet :: WWW/HTTP :: Browsers
Classifier: Topic :: Text Processing :: Markup :: HTML
Classifier: Topic :: Scientific/Engineering :: Artificial Intelligence
Classifier: License :: OSI Approved :: MIT License
Classifier: Programming Language :: Python :: 3
Classifier: Programming Language :: Python :: 3.8
Classifier: Programming Language :: Python :: 3.9
Classifier: Programming Language :: Python :: 3.10
Classifier: Programming Language :: Python :: 3.11
Classifier: Programming Language :: Python :: 3.12
Classifier: Operating System :: OS Independent
Requires-Python: >=3.8
License-File: LICENSE
Requires-Dist: selenium>=4.15.0
Requires-Dist: beautifulsoup4>=4.12.0
Requires-Dist: lxml>=4.9.0
Requires-Dist: webdriver-manager>=4.0.0
Provides-Extra: dev
Requires-Dist: pytest>=7.0.0; extra == "dev"
Requires-Dist: pytest-cov>=4.0.0; extra == "dev"
Requires-Dist: black>=23.0.0; extra == "dev"
Requires-Dist: isort>=5.12.0; extra == "dev"
Requires-Dist: flake8>=6.0.0; extra == "dev"
Dynamic: license-file
